paladiner_mcp_demo/__init__.py
paladiner_mcp_demo-0.1.0.dist-info/METADATA
paladiner_mcp_demo-0.1.0.dist-info/WHEEL
paladiner_mcp_demo-0.1.0.dist-info/entry_points.txt
paladiner_mcp_demo-0.1.0.dist-info/RECORD
